morphonet/__init__.py
morphonet/lineage_communication.py
morphonet/net.py
morphonet/tools.py
morphonet/ImageHandling/IO.py
morphonet/ImageHandling/__init__.py
morphonet/ImageHandling/inrimage.py
morphonet/ImageHandling/metaimage.py
morphonet/ImageHandling/spatial_image.py
morphonet/data/__init__.py
morphonet/data/data.py
morphonet/data/dataproperty.py
morphonet/data/dataset.py
morphonet/data/default_parameters.py
morphonet/data/utils.py
morphonet/plot/Annotation.py
morphonet/plot/Dataset.py
morphonet/plot/Object.py
morphonet/plot/Property.py
morphonet/plot/ScikitProperty.py
morphonet/plot/Server.py
morphonet/plot/__init__.py
morphonet/plot/plot.py
morphonet/plugins/MorphoPlugin.py
morphonet/plugins/__init__.py
morphonet/plugins/functions.py
morphonet/plugins/DeNovoSeed/Seedax.py
morphonet/plugins/DeNovoSeed/Seedero.py
morphonet/plugins/DeNovoSeed/Seedin.py
morphonet/plugins/DeNovoSeed/Seedio.py
morphonet/plugins/DeNovoSeed/Seedis.py
morphonet/plugins/DeNovoSeed/__init__.py
morphonet/plugins/DeNovoSegmentation/BinBox.py
morphonet/plugins/DeNovoSegmentation/BinCha.py
morphonet/plugins/DeNovoSegmentation/Binarize.py
morphonet/plugins/DeNovoSegmentation/CellPoseTrain.py
morphonet/plugins/DeNovoSegmentation/CellposePredict.py
morphonet/plugins/DeNovoSegmentation/Mars.py
morphonet/plugins/DeNovoSegmentation/StardistPredict.py
morphonet/plugins/DeNovoSegmentation/StardistTrain.py
morphonet/plugins/DeNovoSegmentation/__init__.py
morphonet/plugins/EditTemporalLinks/Addlink.py
morphonet/plugins/EditTemporalLinks/Delink.py
morphonet/plugins/EditTemporalLinks/Tracko.py
morphonet/plugins/EditTemporalLinks/__init__.py
morphonet/plugins/PropagateSegmentation/Propa.py
morphonet/plugins/PropagateSegmentation/Prope.py
morphonet/plugins/PropagateSegmentation/Propi.py
morphonet/plugins/PropagateSegmentation/Propro.py
morphonet/plugins/PropagateSegmentation/TrackAndFuse.py
morphonet/plugins/PropagateSegmentation/__init__.py
morphonet-2.2.25.dist-info/LICENSE
morphonet-2.2.25.dist-info/METADATA
morphonet-2.2.25.dist-info/WHEEL
morphonet-2.2.25.dist-info/top_level.txt
morphonet-2.2.25.dist-info/RECORD
