Metadata-Version: 2.1
Name: morphonet
Version: 2.2.25
Summary: Python API to interact with MorphoNet
Home-page: https://gitlab.inria.fr/efaure/MorphoNet
Author: Emmanuel Faure
Author-email: api@morphonet.org
Classifier: Programming Language :: Python
Classifier: License :: OSI Approved
Classifier: Natural Language :: English
Classifier: Operating System :: OS Independent
Classifier: Programming Language :: Python :: 3.7
Classifier: Topic :: Scientific/Engineering :: Visualization
License-File: LICENSE
Requires-Dist: requests
Requires-Dist: numpy
Requires-Dist: vtk
Requires-Dist: imageio
Requires-Dist: scikit-image
Requires-Dist: scipy
Requires-Dist: nibabel
Requires-Dist: imageio-ffmpeg
Requires-Dist: tqdm
Requires-Dist: SimpleITK
Requires-Dist: psutil
Requires-Dist: scikit-learn
